argusclient/__init__.py
argusclient/client.py
argusclient/dashboardtags.py
argusclient/model.py
monexclient/__init__.py
monexclient/monexclient.py
argusclient-1.7.dist-info/LICENSE.txt
argusclient-1.7.dist-info/METADATA
argusclient-1.7.dist-info/WHEEL
argusclient-1.7.dist-info/top_level.txt
argusclient-1.7.dist-info/zip-safe
argusclient-1.7.dist-info/RECORD
