Metadata-Version: 2.1
Name: argusclient
Version: 1.7
Summary: Minimal client library for Argus webservice REST API
Home-page: https://github.com/SalesforceEng/argusclient
Author: Hari Krishna Dara
Author-email: hdara@salesforce.com
License: BSD-3-Clause
Keywords: argus
Classifier: Development Status :: 5 - Production/Stable
Classifier: Programming Language :: Python :: 3.8
Classifier: License :: OSI Approved :: BSD License
Classifier: Intended Audience :: Developers
Classifier: Topic :: System :: Monitoring
License-File: LICENSE.txt
Requires-Dist: six (>=1.12.0)
Requires-Dist: requests (>=2.26.0)
Requires-Dist: lxml (>=4.6.3)
